refusal_cleaner/__init__.py
refusal_cleaner/backfiller.py
refusal_cleaner/classifier.py
refusal_cleaner/cli.py
refusal_cleaner/pipeline.py
refusal_cleaner/rewriter.py
refusal_cleaner/utils/__init__.py
refusal_cleaner/utils/fetch_datasets.py
refusal_cleaner/utils/make_head_copy.py
refusal_cleaner/utils/utils.py
refusal_cleaner-0.2.0.dist-info/licenses/LICENSE
refusal_cleaner-0.2.0.dist-info/METADATA
refusal_cleaner-0.2.0.dist-info/WHEEL
refusal_cleaner-0.2.0.dist-info/entry_points.txt
refusal_cleaner-0.2.0.dist-info/top_level.txt
refusal_cleaner-0.2.0.dist-info/RECORD
