Metadata-Version: 2.4
Name: refusal-cleaner
Version: 0.2.0
Summary: A pipeline for cleaning instruction datasets by removing refusals and rewriting prompts into safe, answerable questions.
Author-email: Joshua Gompert <joshua.gompert@gmail.com>
License: MIT License
Project-URL: Homepage, https://github.com/ginkorea/refusal-cleaner
Project-URL: Issues, https://github.com/ginkorea/refusal-cleaner/issues
Requires-Python: >=3.10
License-File: LICENSE
Requires-Dist: openai>=1.0.0
Requires-Dist: datasets
Requires-Dist: python-dotenv
Dynamic: license-file
